step2/clock-div.sv
// Clock interno de 12MHz
module clock_divider #(

    // Parameters
    parameter   MODULO  = 6000000
) (
    
    // Inputs
    input   clk,
    input   rst,
    
    // Outputs
    output  tick
);

    // Calculate number of bits needed for the counter
    localparam WIDTH = (MODULO == 1) ? 1 : $clog2(MODULO);

    // Internal storage elements
    reg [WIDTH-1:0] count = 0;

    // Tick is high for one clock cycle at max count
    assign tick = (count == MODULO - 1) ? 1'b1 : 1'b0;
    
    // Count up, reset on tick pulse
    always @ (posedge clk or posedge rst) begin
        if (rst == 1'b1) begin
            count <= 0;
        end else if (tick == 1'b1) begin
            count <= 0;
        end else begin
            count <= count + 1;
        end
    end
    
endmodule

step3/led_blinky.sv
module led_blinky(
    //Inputs
    input       clk,
    input		rst,

    //Outputs
    output [4:0] led
);

    bit [20:0][4:0] m_data;
    int count = 0;
    reg [4:0] out_reg_led = 5'b00000;

    initial begin 
        for (int i = 0; i < $size(m_data); i++) begin
            $display ("m_data[%0d] = %b (0x%0h)", i, m_data[i], m_data[i]);
            m_data[i] = i;
        end
    end

    // Internal signals
	wire rst_signal;
    wire clk_local;
	
	//Invert active-low button
	assign rst_signal = ~rst;
    assign led = out_reg_led;
    
    clock_divider #(.MODULO(8)) div_clock (
        .clk(clk),
        .rst(rst_signal),
        .tick(clk_local)
    );

    always @ (posedge clk_local or posedge rst_signal) begin
        if (rst_signal == 1'b1) begin
            out_reg_led <= 5'b00000;
        end else begin
            if (count < $size(m_data)) begin
                count <= count + 1;
                out_reg_led <= m_data[count];
            end else begin
                out_reg_led <= 5'b00000;
                count <= 0;
            end
        end
    end

endmodule

step3/led_blinky_tb.sv
// Defines timescale for simulation: <time_unit> / <time_precision>
// This specific keyword is brought by Icarus Verilog simulator, but it could be different for others
//Also the name _tb.v in this file is used by apio for testbench
`timescale 1 ns / 10 ps



// Define our testbench
module led_blinky_tb();
	
	//Internal signals
	wire	[4:0] out;
	
	//Storage elements (Set initial values to 0)
	reg		clk = 0;
	reg		rst = 0;
	
	//Simulation time: 10000 * 1 ns = 10 us
	localparam DURATION = 40000;
	
	//Funcion reset
	task apply_reset ();
		#10  rst = 0;
		#1  rst = 1;
	endtask


	// Generate clock signal: 1 / ((2 * 41.67) * 1 ns) = 11,999,040.08 MHz
	always begin
		
		//Delay for 41.67 time units
		//10 ps precision means that 41.667 is rounded to 41.67 ns
		#41.667
		
		//Toggle Clock line
		clk = ~clk;
	end
	
	// Instatiate the unit under test (UUT)
	led_blinky uut (
		.clk(clk),
		.rst(rst),
		.led(out)
	);
	
	//Pulse reset line high at the beginning
	initial begin
		apply_reset();
	end
	
	//Run simulation (output to .vcd files)
	initial begin
		
		//Create simulation output file
		$dumpfile("led_blinky.vcd");
		$dumpvars(0, led_blinky_tb);
		
		// Wait for given amount of time for simulation to complete
		#(DURATION)
		
		// Notify and end simulation
		$display("Finished!");
		$finish;
	end
	
endmodule

step3/led_blinky.vcd
$date
	Sat Jul  5 17:21:55 2025
$end
$version
	Icarus Verilog
$end
$timescale
	10ps
$end
$scope module led_blinky_tb $end
$var wire 5 ! out [4:0] $end
$var parameter 32 " DURATION $end
$var reg 1 # clk $end
$var reg 1 $ rst $end
$scope module uut $end
$var wire 1 # clk $end
$var wire 5 % led [4:0] $end
$var wire 1 $ rst $end
$var wire 1 & rst_signal $end
$var wire 1 ' clk_local $end
$var reg 5 ( out_reg_led [4:0] $end
$var integer 32 ) count [31:0] $end
$var reg 105 * m_data [104:0] $end
$scope module div_clock $end
$var wire 1 # clk $end
$var wire 1 & rst $end
$var wire 1 ' tick $end
$var parameter 32 + MODULO $end
$var parameter 32 , WIDTH $end
$var reg 3 - count [2:0] $end
$upscope $end
$scope begin $ivl_for_loop0 $end
$var integer 32 . i [31:0] $end
$upscope $end
$upscope $end
$scope task apply_reset $end
$upscope $end
$upscope $end
$enddefinitions $end
$comment Show the parameter values. $end
$dumpall
b11 ,
b1000 +
b1001110001000000 "
$end
#0
$dumpvars
b10101 .
b0 -
b101001001110010100011000001111011100110101100010110101001001010000011100110001010010000011000100000100000 *
b0 )
b0 (
0'
1&
b0 %
0$
0#
b0 !
$end
#1100
0&
1$
#4167
b1 -
1#
#8334
0#
#12501
b10 -
1#
#16668
0#
#20835
b11 -
1#
#25002
0#
#29169
b100 -
1#
#33336
0#
#37503
b101 -
1#
#41670
0#
#45837
b110 -
1#
#50004
0#
#54171
b1 )
1'
b111 -
1#
#58338
0#
#62505
0'
b0 -
1#
#66672
0#
#70839
b1 -
1#
#75006
0#
#79173
b10 -
1#
#83340
0#
#87507
b11 -
1#
#91674
0#
#95841
b100 -
1#
#100008
0#
#104175
b101 -
1#
#108342
0#
#112509
b110 -
1#
#116676
0#
#120843
b1 !
b1 %
b1 (
b10 )
1'
b111 -
1#
#125010
0#
#129177
0'
b0 -
1#
#133344
0#
#137511
b1 -
1#
#141678
0#
#145845
b10 -
1#
#150012
0#
#154179
b11 -
1#
#158346
0#
#162513
b100 -
1#
#166680
0#
#170847
b101 -
1#
#175014
0#
#179181
b110 -
1#
#183348
0#
#187515
b10 !
b10 %
b10 (
b11 )
1'
b111 -
1#
#191682
0#
#195849
0'
b0 -
1#
#200016
0#
#204183
b1 -
1#
#208350
0#
#212517
b10 -
1#
#216684
0#
#220851
b11 -
1#
#225018
0#
#229185
b100 -
1#
#233352
0#
#237519
b101 -
1#
#241686
0#
#245853
b110 -
1#
#250020
0#
#254187
b11 !
b11 %
b11 (
b100 )
1'
b111 -
1#
#258354
0#
#262521
0'
b0 -
1#
#266688
0#
#270855
b1 -
1#
#275022
0#
#279189
b10 -
1#
#283356
0#
#287523
b11 -
1#
#291690
0#
#295857
b100 -
1#
#300024
0#
#304191
b101 -
1#
#308358
0#
#312525
b110 -
1#
#316692
0#
#320859
b100 !
b100 %
b100 (
b101 )
1'
b111 -
1#
#325026
0#
#329193
0'
b0 -
1#
#333360
0#
#337527
b1 -
1#
#341694
0#
#345861
b10 -
1#
#350028
0#
#354195
b11 -
1#
#358362
0#
#362529
b100 -
1#
#366696
0#
#370863
b101 -
1#
#375030
0#
#379197
b110 -
1#
#383364
0#
#387531
b101 !
b101 %
b101 (
b110 )
1'
b111 -
1#
#391698
0#
#395865
0'
b0 -
1#
#400032
0#
#404199
b1 -
1#
#408366
0#
#412533
b10 -
1#
#416700
0#
#420867
b11 -
1#
#425034
0#
#429201
b100 -
1#
#433368
0#
#437535
b101 -
1#
#441702
0#
#445869
b110 -
1#
#450036
0#
#454203
b110 !
b110 %
b110 (
b111 )
1'
b111 -
1#
#458370
0#
#462537
0'
b0 -
1#
#466704
0#
#470871
b1 -
1#
#475038
0#
#479205
b10 -
1#
#483372
0#
#487539
b11 -
1#
#491706
0#
#495873
b100 -
1#
#500040
0#
#504207
b101 -
1#
#508374
0#
#512541
b110 -
1#
#516708
0#
#520875
b111 !
b111 %
b111 (
b1000 )
1'
b111 -
1#
#525042
0#
#529209
0'
b0 -
1#
#533376
0#
#537543
b1 -
1#
#541710
0#
#545877
b10 -
1#
#550044
0#
#554211
b11 -
1#
#558378
0#
#562545
b100 -
1#
#566712
0#
#570879
b101 -
1#
#575046
0#
#579213
b110 -
1#
#583380
0#
#587547
b1000 !
b1000 %
b1000 (
b1001 )
1'
b111 -
1#
#591714
0#
#595881
0'
b0 -
1#
#600048
0#
#604215
b1 -
1#
#608382
0#
#612549
b10 -
1#
#616716
0#
#620883
b11 -
1#
#625050
0#
#629217
b100 -
1#
#633384
0#
#637551
b101 -
1#
#641718
0#
#645885
b110 -
1#
#650052
0#
#654219
b1001 !
b1001 %
b1001 (
b1010 )
1'
b111 -
1#
#658386
0#
#662553
0'
b0 -
1#
#666720
0#
#670887
b1 -
1#
#675054
0#
#679221
b10 -
1#
#683388
0#
#687555
b11 -
1#
#691722
0#
#695889
b100 -
1#
#700056
0#
#704223
b101 -
1#
#708390
0#
#712557
b110 -
1#
#716724
0#
#720891
b1010 !
b1010 %
b1010 (
b1011 )
1'
b111 -
1#
#725058
0#
#729225
0'
b0 -
1#
#733392
0#
#737559
b1 -
1#
#741726
0#
#745893
b10 -
1#
#750060
0#
#754227
b11 -
1#
#758394
0#
#762561
b100 -
1#
#766728
0#
#770895
b101 -
1#
#775062
0#
#779229
b110 -
1#
#783396
0#
#787563
b1011 !
b1011 %
b1011 (
b1100 )
1'
b111 -
1#
#791730
0#
#795897
0'
b0 -
1#
#800064
0#
#804231
b1 -
1#
#808398
0#
#812565
b10 -
1#
#816732
0#
#820899
b11 -
1#
#825066
0#
#829233
b100 -
1#
#833400
0#
#837567
b101 -
1#
#841734
0#
#845901
b110 -
1#
#850068
0#
#854235
b1100 !
b1100 %
b1100 (
b1101 )
1'
b111 -
1#
#858402
0#
#862569
0'
b0 -
1#
#866736
0#
#870903
b1 -
1#
#875070
0#
#879237
b10 -
1#
#883404
0#
#887571
b11 -
1#
#891738
0#
#895905
b100 -
1#
#900072
0#
#904239
b101 -
1#
#908406
0#
#912573
b110 -
1#
#916740
0#
#920907
b1101 !
b1101 %
b1101 (
b1110 )
1'
b111 -
1#
#925074
0#
#929241
0'
b0 -
1#
#933408
0#
#937575
b1 -
1#
#941742
0#
#945909
b10 -
1#
#950076
0#
#954243
b11 -
1#
#958410
0#
#962577
b100 -
1#
#966744
0#
#970911
b101 -
1#
#975078
0#
#979245
b110 -
1#
#983412
0#
#987579
b1110 !
b1110 %
b1110 (
b1111 )
1'
b111 -
1#
#991746
0#
#995913
0'
b0 -
1#
#1000080
0#
#1004247
b1 -
1#
#1008414
0#
#1012581
b10 -
1#
#1016748
0#
#1020915
b11 -
1#
#1025082
0#
#1029249
b100 -
1#
#1033416
0#
#1037583
b101 -
1#
#1041750
0#
#1045917
b110 -
1#
#1050084
0#
#1054251
b1111 !
b1111 %
b1111 (
b10000 )
1'
b111 -
1#
#1058418
0#
#1062585
0'
b0 -
1#
#1066752
0#
#1070919
b1 -
1#
#1075086
0#
#1079253
b10 -
1#
#1083420
0#
#1087587
b11 -
1#
#1091754
0#
#1095921
b100 -
1#
#1100088
0#
#1104255
b101 -
1#
#1108422
0#
#1112589
b110 -
1#
#1116756
0#
#1120923
b10000 !
b10000 %
b10000 (
b10001 )
1'
b111 -
1#
#1125090
0#
#1129257
0'
b0 -
1#
#1133424
0#
#1137591
b1 -
1#
#1141758
0#
#1145925
b10 -
1#
#1150092
0#
#1154259
b11 -
1#
#1158426
0#
#1162593
b100 -
1#
#1166760
0#
#1170927
b101 -
1#
#1175094
0#
#1179261
b110 -
1#
#1183428
0#
#1187595
b10001 !
b10001 %
b10001 (
b10010 )
1'
b111 -
1#
#1191762
0#
#1195929
0'
b0 -
1#
#1200096
0#
#1204263
b1 -
1#
#1208430
0#
#1212597
b10 -
1#
#1216764
0#
#1220931
b11 -
1#
#1225098
0#
#1229265
b100 -
1#
#1233432
0#
#1237599
b101 -
1#
#1241766
0#
#1245933
b110 -
1#
#1250100
0#
#1254267
b10010 !
b10010 %
b10010 (
b10011 )
1'
b111 -
1#
#1258434
0#
#1262601
0'
b0 -
1#
#1266768
0#
#1270935
b1 -
1#
#1275102
0#
#1279269
b10 -
1#
#1283436
0#
#1287603
b11 -
1#
#1291770
0#
#1295937
b100 -
1#
#1300104
0#
#1304271
b101 -
1#
#1308438
0#
#1312605
b110 -
1#
#1316772
0#
#1320939
b10011 !
b10011 %
b10011 (
b10100 )
1'
b111 -
1#
#1325106
0#
#1329273
0'
b0 -
1#
#1333440
0#
#1337607
b1 -
1#
#1341774
0#
#1345941
b10 -
1#
#1350108
0#
#1354275
b11 -
1#
#1358442
0#
#1362609
b100 -
1#
#1366776
0#
#1370943
b101 -
1#
#1375110
0#
#1379277
b110 -
1#
#1383444
0#
#1387611
b10100 !
b10100 %
b10100 (
b10101 )
1'
b111 -
1#
#1391778
0#
#1395945
0'
b0 -
1#
#1400112
0#
#1404279
b1 -
1#
#1408446
0#
#1412613
b10 -
1#
#1416780
0#
#1420947
b11 -
1#
#1425114
0#
#1429281
b100 -
1#
#1433448
0#
#1437615
b101 -
1#
#1441782
0#
#1445949
b110 -
1#
#1450116
0#
#1454283
b0 )
b0 !
b0 %
b0 (
1'
b111 -
1#
#1458450
0#
#1462617
0'
b0 -
1#
#1466784
0#
#1470951
b1 -
1#
#1475118
0#
#1479285
b10 -
1#
#1483452
0#
#1487619
b11 -
1#
#1491786
0#
#1495953
b100 -
1#
#1500120
0#
#1504287
b101 -
1#
#1508454
0#
#1512621
b110 -
1#
#1516788
0#
#1520955
b1 )
1'
b111 -
1#
#1525122
0#
#1529289
0'
b0 -
1#
#1533456
0#
#1537623
b1 -
1#
#1541790
0#
#1545957
b10 -
1#
#1550124
0#
#1554291
b11 -
1#
#1558458
0#
#1562625
b100 -
1#
#1566792
0#
#1570959
b101 -
1#
#1575126
0#
#1579293
b110 -
1#
#1583460
0#
#1587627
b1 !
b1 %
b1 (
b10 )
1'
b111 -
1#
#1591794
0#
#1595961
0'
b0 -
1#
#1600128
0#
#1604295
b1 -
1#
#1608462
0#
#1612629
b10 -
1#
#1616796
0#
#1620963
b11 -
1#
#1625130
0#
#1629297
b100 -
1#
#1633464
0#
#1637631
b101 -
1#
#1641798
0#
#1645965
b110 -
1#
#1650132
0#
#1654299
b10 !
b10 %
b10 (
b11 )
1'
b111 -
1#
#1658466
0#
#1662633
0'
b0 -
1#
#1666800
0#
#1670967
b1 -
1#
#1675134
0#
#1679301
b10 -
1#
#1683468
0#
#1687635
b11 -
1#
#1691802
0#
#1695969
b100 -
1#
#1700136
0#
#1704303
b101 -
1#
#1708470
0#
#1712637
b110 -
1#
#1716804
0#
#1720971
b11 !
b11 %
b11 (
b100 )
1'
b111 -
1#
#1725138
0#
#1729305
0'
b0 -
1#
#1733472
0#
#1737639
b1 -
1#
#1741806
0#
#1745973
b10 -
1#
#1750140
0#
#1754307
b11 -
1#
#1758474
0#
#1762641
b100 -
1#
#1766808
0#
#1770975
b101 -
1#
#1775142
0#
#1779309
b110 -
1#
#1783476
0#
#1787643
b100 !
b100 %
b100 (
b101 )
1'
b111 -
1#
#1791810
0#
#1795977
0'
b0 -
1#
#1800144
0#
#1804311
b1 -
1#
#1808478
0#
#1812645
b10 -
1#
#1816812
0#
#1820979
b11 -
1#
#1825146
0#
#1829313
b100 -
1#
#1833480
0#
#1837647
b101 -
1#
#1841814
0#
#1845981
b110 -
1#
#1850148
0#
#1854315
b101 !
b101 %
b101 (
b110 )
1'
b111 -
1#
#1858482
0#
#1862649
0'
b0 -
1#
#1866816
0#
#1870983
b1 -
1#
#1875150
0#
#1879317
b10 -
1#
#1883484
0#
#1887651
b11 -
1#
#1891818
0#
#1895985
b100 -
1#
#1900152
0#
#1904319
b101 -
1#
#1908486
0#
#1912653
b110 -
1#
#1916820
0#
#1920987
b110 !
b110 %
b110 (
b111 )
1'
b111 -
1#
#1925154
0#
#1929321
0'
b0 -
1#
#1933488
0#
#1937655
b1 -
1#
#1941822
0#
#1945989
b10 -
1#
#1950156
0#
#1954323
b11 -
1#
#1958490
0#
#1962657
b100 -
1#
#1966824
0#
#1970991
b101 -
1#
#1975158
0#
#1979325
b110 -
1#
#1983492
0#
#1987659
b111 !
b111 %
b111 (
b1000 )
1'
b111 -
1#
#1991826
0#
#1995993
0'
b0 -
1#
#2000160
0#
#2004327
b1 -
1#
#2008494
0#
#2012661
b10 -
1#
#2016828
0#
#2020995
b11 -
1#
#2025162
0#
#2029329
b100 -
1#
#2033496
0#
#2037663
b101 -
1#
#2041830
0#
#2045997
b110 -
1#
#2050164
0#
#2054331
b1000 !
b1000 %
b1000 (
b1001 )
1'
b111 -
1#
#2058498
0#
#2062665
0'
b0 -
1#
#2066832
0#
#2070999
b1 -
1#
#2075166
0#
#2079333
b10 -
1#
#2083500
0#
#2087667
b11 -
1#
#2091834
0#
#2096001
b100 -
1#
#2100168
0#
#2104335
b101 -
1#
#2108502
0#
#2112669
b110 -
1#
#2116836
0#
#2121003
b1001 !
b1001 %
b1001 (
b1010 )
1'
b111 -
1#
#2125170
0#
#2129337
0'
b0 -
1#
#2133504
0#
#2137671
b1 -
1#
#2141838
0#
#2146005
b10 -
1#
#2150172
0#
#2154339
b11 -
1#
#2158506
0#
#2162673
b100 -
1#
#2166840
0#
#2171007
b101 -
1#
#2175174
0#
#2179341
b110 -
1#
#2183508
0#
#2187675
b1010 !
b1010 %
b1010 (
b1011 )
1'
b111 -
1#
#2191842
0#
#2196009
0'
b0 -
1#
#2200176
0#
#2204343
b1 -
1#
#2208510
0#
#2212677
b10 -
1#
#2216844
0#
#2221011
b11 -
1#
#2225178
0#
#2229345
b100 -
1#
#2233512
0#
#2237679
b101 -
1#
#2241846
0#
#2246013
b110 -
1#
#2250180
0#
#2254347
b1011 !
b1011 %
b1011 (
b1100 )
1'
b111 -
1#
#2258514
0#
#2262681
0'
b0 -
1#
#2266848
0#
#2271015
b1 -
1#
#2275182
0#
#2279349
b10 -
1#
#2283516
0#
#2287683
b11 -
1#
#2291850
0#
#2296017
b100 -
1#
#2300184
0#
#2304351
b101 -
1#
#2308518
0#
#2312685
b110 -
1#
#2316852
0#
#2321019
b1100 !
b1100 %
b1100 (
b1101 )
1'
b111 -
1#
#2325186
0#
#2329353
0'
b0 -
1#
#2333520
0#
#2337687
b1 -
1#
#2341854
0#
#2346021
b10 -
1#
#2350188
0#
#2354355
b11 -
1#
#2358522
0#
#2362689
b100 -
1#
#2366856
0#
#2371023
b101 -
1#
#2375190
0#
#2379357
b110 -
1#
#2383524
0#
#2387691
b1101 !
b1101 %
b1101 (
b1110 )
1'
b111 -
1#
#2391858
0#
#2396025
0'
b0 -
1#
#2400192
0#
#2404359
b1 -
1#
#2408526
0#
#2412693
b10 -
1#
#2416860
0#
#2421027
b11 -
1#
#2425194
0#
#2429361
b100 -
1#
#2433528
0#
#2437695
b101 -
1#
#2441862
0#
#2446029
b110 -
1#
#2450196
0#
#2454363
b1110 !
b1110 %
b1110 (
b1111 )
1'
b111 -
1#
#2458530
0#
#2462697
0'
b0 -
1#
#2466864
0#
#2471031
b1 -
1#
#2475198
0#
#2479365
b10 -
1#
#2483532
0#
#2487699
b11 -
1#
#2491866
0#
#2496033
b100 -
1#
#2500200
0#
#2504367
b101 -
1#
#2508534
0#
#2512701
b110 -
1#
#2516868
0#
#2521035
b1111 !
b1111 %
b1111 (
b10000 )
1'
b111 -
1#
#2525202
0#
#2529369
0'
b0 -
1#
#2533536
0#
#2537703
b1 -
1#
#2541870
0#
#2546037
b10 -
1#
#2550204
0#
#2554371
b11 -
1#
#2558538
0#
#2562705
b100 -
1#
#2566872
0#
#2571039
b101 -
1#
#2575206
0#
#2579373
b110 -
1#
#2583540
0#
#2587707
b10000 !
b10000 %
b10000 (
b10001 )
1'
b111 -
1#
#2591874
0#
#2596041
0'
b0 -
1#
#2600208
0#
#2604375
b1 -
1#
#2608542
0#
#2612709
b10 -
1#
#2616876
0#
#2621043
b11 -
1#
#2625210
0#
#2629377
b100 -
1#
#2633544
0#
#2637711
b101 -
1#
#2641878
0#
#2646045
b110 -
1#
#2650212
0#
#2654379
b10001 !
b10001 %
b10001 (
b10010 )
1'
b111 -
1#
#2658546
0#
#2662713
0'
b0 -
1#
#2666880
0#
#2671047
b1 -
1#
#2675214
0#
#2679381
b10 -
1#
#2683548
0#
#2687715
b11 -
1#
#2691882
0#
#2696049
b100 -
1#
#2700216
0#
#2704383
b101 -
1#
#2708550
0#
#2712717
b110 -
1#
#2716884
0#
#2721051
b10010 !
b10010 %
b10010 (
b10011 )
1'
b111 -
1#
#2725218
0#
#2729385
0'
b0 -
1#
#2733552
0#
#2737719
b1 -
1#
#2741886
0#
#2746053
b10 -
1#
#2750220
0#
#2754387
b11 -
1#
#2758554
0#
#2762721
b100 -
1#
#2766888
0#
#2771055
b101 -
1#
#2775222
0#
#2779389
b110 -
1#
#2783556
0#
#2787723
b10011 !
b10011 %
b10011 (
b10100 )
1'
b111 -
1#
#2791890
0#
#2796057
0'
b0 -
1#
#2800224
0#
#2804391
b1 -
1#
#2808558
0#
#2812725
b10 -
1#
#2816892
0#
#2821059
b11 -
1#
#2825226
0#
#2829393
b100 -
1#
#2833560
0#
#2837727
b101 -
1#
#2841894
0#
#2846061
b110 -
1#
#2850228
0#
#2854395
b10100 !
b10100 %
b10100 (
b10101 )
1'
b111 -
1#
#2858562
0#
#2862729
0'
b0 -
1#
#2866896
0#
#2871063
b1 -
1#
#2875230
0#
#2879397
b10 -
1#
#2883564
0#
#2887731
b11 -
1#
#2891898
0#
#2896065
b100 -
1#
#2900232
0#
#2904399
b101 -
1#
#2908566
0#
#2912733
b110 -
1#
#2916900
0#
#2921067
b0 )
b0 !
b0 %
b0 (
1'
b111 -
1#
#2925234
0#
#2929401
0'
b0 -
1#
#2933568
0#
#2937735
b1 -
1#
#2941902
0#
#2946069
b10 -
1#
#2950236
0#
#2954403
b11 -
1#
#2958570
0#
#2962737
b100 -
1#
#2966904
0#
#2971071
b101 -
1#
#2975238
0#
#2979405
b110 -
1#
#2983572
0#
#2987739
b1 )
1'
b111 -
1#
#2991906
0#
#2996073
0'
b0 -
1#
#3000240
0#
#3004407
b1 -
1#
#3008574
0#
#3012741
b10 -
1#
#3016908
0#
#3021075
b11 -
1#
#3025242
0#
#3029409
b100 -
1#
#3033576
0#
#3037743
b101 -
1#
#3041910
0#
#3046077
b110 -
1#
#3050244
0#
#3054411
b1 !
b1 %
b1 (
b10 )
1'
b111 -
1#
#3058578
0#
#3062745
0'
b0 -
1#
#3066912
0#
#3071079
b1 -
1#
#3075246
0#
#3079413
b10 -
1#
#3083580
0#
#3087747
b11 -
1#
#3091914
0#
#3096081
b100 -
1#
#3100248
0#
#3104415
b101 -
1#
#3108582
0#
#3112749
b110 -
1#
#3116916
0#
#3121083
b10 !
b10 %
b10 (
b11 )
1'
b111 -
1#
#3125250
0#
#3129417
0'
b0 -
1#
#3133584
0#
#3137751
b1 -
1#
#3141918
0#
#3146085
b10 -
1#
#3150252
0#
#3154419
b11 -
1#
#3158586
0#
#3162753
b100 -
1#
#3166920
0#
#3171087
b101 -
1#
#3175254
0#
#3179421
b110 -
1#
#3183588
0#
#3187755
b11 !
b11 %
b11 (
b100 )
1'
b111 -
1#
#3191922
0#
#3196089
0'
b0 -
1#
#3200256
0#
#3204423
b1 -
1#
#3208590
0#
#3212757
b10 -
1#
#3216924
0#
#3221091
b11 -
1#
#3225258
0#
#3229425
b100 -
1#
#3233592
0#
#3237759
b101 -
1#
#3241926
0#
#3246093
b110 -
1#
#3250260
0#
#3254427
b100 !
b100 %
b100 (
b101 )
1'
b111 -
1#
#3258594
0#
#3262761
0'
b0 -
1#
#3266928
0#
#3271095
b1 -
1#
#3275262
0#
#3279429
b10 -
1#
#3283596
0#
#3287763
b11 -
1#
#3291930
0#
#3296097
b100 -
1#
#3300264
0#
#3304431
b101 -
1#
#3308598
0#
#3312765
b110 -
1#
#3316932
0#
#3321099
b101 !
b101 %
b101 (
b110 )
1'
b111 -
1#
#3325266
0#
#3329433
0'
b0 -
1#
#3333600
0#
#3337767
b1 -
1#
#3341934
0#
#3346101
b10 -
1#
#3350268
0#
#3354435
b11 -
1#
#3358602
0#
#3362769
b100 -
1#
#3366936
0#
#3371103
b101 -
1#
#3375270
0#
#3379437
b110 -
1#
#3383604
0#
#3387771
b110 !
b110 %
b110 (
b111 )
1'
b111 -
1#
#3391938
0#
#3396105
0'
b0 -
1#
#3400272
0#
#3404439
b1 -
1#
#3408606
0#
#3412773
b10 -
1#
#3416940
0#
#3421107
b11 -
1#
#3425274
0#
#3429441
b100 -
1#
#3433608
0#
#3437775
b101 -
1#
#3441942
0#
#3446109
b110 -
1#
#3450276
0#
#3454443
b111 !
b111 %
b111 (
b1000 )
1'
b111 -
1#
#3458610
0#
#3462777
0'
b0 -
1#
#3466944
0#
#3471111
b1 -
1#
#3475278
0#
#3479445
b10 -
1#
#3483612
0#
#3487779
b11 -
1#
#3491946
0#
#3496113
b100 -
1#
#3500280
0#
#3504447
b101 -
1#
#3508614
0#
#3512781
b110 -
1#
#3516948
0#
#3521115
b1000 !
b1000 %
b1000 (
b1001 )
1'
b111 -
1#
#3525282
0#
#3529449
0'
b0 -
1#
#3533616
0#
#3537783
b1 -
1#
#3541950
0#
#3546117
b10 -
1#
#3550284
0#
#3554451
b11 -
1#
#3558618
0#
#3562785
b100 -
1#
#3566952
0#
#3571119
b101 -
1#
#3575286
0#
#3579453
b110 -
1#
#3583620
0#
#3587787
b1001 !
b1001 %
b1001 (
b1010 )
1'
b111 -
1#
#3591954
0#
#3596121
0'
b0 -
1#
#3600288
0#
#3604455
b1 -
1#
#3608622
0#
#3612789
b10 -
1#
#3616956
0#
#3621123
b11 -
1#
#3625290
0#
#3629457
b100 -
1#
#3633624
0#
#3637791
b101 -
1#
#3641958
0#
#3646125
b110 -
1#
#3650292
0#
#3654459
b1010 !
b1010 %
b1010 (
b1011 )
1'
b111 -
1#
#3658626
0#
#3662793
0'
b0 -
1#
#3666960
0#
#3671127
b1 -
1#
#3675294
0#
#3679461
b10 -
1#
#3683628
0#
#3687795
b11 -
1#
#3691962
0#
#3696129
b100 -
1#
#3700296
0#
#3704463
b101 -
1#
#3708630
0#
#3712797
b110 -
1#
#3716964
0#
#3721131
b1011 !
b1011 %
b1011 (
b1100 )
1'
b111 -
1#
#3725298
0#
#3729465
0'
b0 -
1#
#3733632
0#
#3737799
b1 -
1#
#3741966
0#
#3746133
b10 -
1#
#3750300
0#
#3754467
b11 -
1#
#3758634
0#
#3762801
b100 -
1#
#3766968
0#
#3771135
b101 -
1#
#3775302
0#
#3779469
b110 -
1#
#3783636
0#
#3787803
b1100 !
b1100 %
b1100 (
b1101 )
1'
b111 -
1#
#3791970
0#
#3796137
0'
b0 -
1#
#3800304
0#
#3804471
b1 -
1#
#3808638
0#
#3812805
b10 -
1#
#3816972
0#
#3821139
b11 -
1#
#3825306
0#
#3829473
b100 -
1#
#3833640
0#
#3837807
b101 -
1#
#3841974
0#
#3846141
b110 -
1#
#3850308
0#
#3854475
b1101 !
b1101 %
b1101 (
b1110 )
1'
b111 -
1#
#3858642
0#
#3862809
0'
b0 -
1#
#3866976
0#
#3871143
b1 -
1#
#3875310
0#
#3879477
b10 -
1#
#3883644
0#
#3887811
b11 -
1#
#3891978
0#
#3896145
b100 -
1#
#3900312
0#
#3904479
b101 -
1#
#3908646
0#
#3912813
b110 -
1#
#3916980
0#
#3921147
b1110 !
b1110 %
b1110 (
b1111 )
1'
b111 -
1#
#3925314
0#
#3929481
0'
b0 -
1#
#3933648
0#
#3937815
b1 -
1#
#3941982
0#
#3946149
b10 -
1#
#3950316
0#
#3954483
b11 -
1#
#3958650
0#
#3962817
b100 -
1#
#3966984
0#
#3971151
b101 -
1#
#3975318
0#
#3979485
b110 -
1#
#3983652
0#
#3987819
b1111 !
b1111 %
b1111 (
b10000 )
1'
b111 -
1#
#3991986
0#
#3996153
0'
b0 -
1#
