clock-divider/clock-div.sv
module clock_divider #(

    // Parameters
    parameter   MODULO  = 6000000
) (
    
    // Inputs
    input   clk,
    input   rst,
    
    // Outputs
    output  tick
);

    // Calculate number of bits needed for the counter
    localparam WIDTH = (MODULO == 1) ? 1 : $clog2(MODULO);

    // Internal storage elements
    reg [WIDTH-1:0] count = 0;

    // Tick is high for one clock cycle at max count
    assign tick = (count == MODULO - 1) ? 1'b1 : 1'b0;
    
    // Count up, reset on tick pulse
    always @ (posedge clk or posedge rst) begin
        if (rst == 1'b1) begin
            count <= 0;
        end else if (tick == 1'b1) begin
            count <= 0;
        end else begin
            count <= count + 1;
        end
    end
    
endmodule

clock-divider/clk-div_tb.sv
// Defines timescale for simulation: <time_unit> / <time_precision>
// This specific keyword is brought by Icarus Verilog simulator, but it could be different for others
//Also the name _tb.v in this file is used by apio for testbench
`timescale 1 ns / 10 ps



// Define our testbench
module clock_divider_tb();
	
	//Internal signals
	wire	out;
	
	//Storage elements (Set initial values to 0)
	reg		clk = 0;
	reg		rst = 0;
	
	//Simulation time: 10000 * 1 ns = 10 us
	localparam DURATION = 10000;
	
	//Funcion reset
	task apply_reset ();
		#10  rst = 1;
		#1  rst = 0;
	endtask


	// Generate clock signal: 1 / ((2 * 41.67) * 1 ns) = 11,999,040.08 MHz
	always begin
		
		//Delay for 41.67 time units
		//10 ps precision means that 41.667 is rounded to 41.67 ns
		#41.667
		
		//Toggle Clock line
		clk = ~clk;
	end
	
	// Instatiate the unit under test (UUT)
	clock_divider #(.MODULO(6000000)) uut (
		.clk(clk),
		.rst(rst),
		.tick(out)
	);
	
	//Pulse reset line high at the beginning
	initial begin
		apply_reset();
	end
	
	//Run simulation (output to .vcd files)
	initial begin
		
		//Create simulation output file
		$dumpfile("clk-div_tb.vcd");
		$dumpvars(0, clock_divider_tb);
		
		// Wait for given amount of time for simulation to complete
		#(DURATION)
		
		// Notify and end simulation
		$display("Finished!");
		$finish;
	end
	
endmodule

clock-divider/clk-div_tb.vcd
$date
	Sat Jun 28 15:40:23 2025
$end
$version
	Icarus Verilog
$end
$timescale
	10ps
$end
$scope module clock_divider_tb $end
$var wire 1 ! out $end
$var parameter 32 " DURATION $end
$var reg 1 # clk $end
$var reg 1 $ rst $end
$scope module uut $end
$var wire 1 # clk $end
$var wire 1 $ rst $end
$var wire 1 ! tick $end
$var parameter 32 % MODULO $end
$var parameter 32 & WIDTH $end
$var reg 23 ' count [22:0] $end
$upscope $end
$scope task apply_reset $end
$upscope $end
$upscope $end
$enddefinitions $end
$comment Show the parameter values. $end
$dumpall
b10111 &
b10110111000110110000000 %
b10011100010000 "
$end
#0
$dumpvars
b0 '
0$
0#
0!
$end
#1000
1$
#1100
0$
#4167
b1 '
1#
#8334
0#
#12501
b10 '
1#
#16668
0#
#20835
b11 '
1#
#25002
0#
#29169
b100 '
1#
#33336
0#
#37503
b101 '
1#
#41670
0#
#45837
b110 '
1#
#50004
0#
#54171
b111 '
1#
#58338
0#
#62505
b1000 '
1#
#66672
0#
#70839
b1001 '
1#
#75006
0#
#79173
b1010 '
1#
#83340
0#
#87507
b1011 '
1#
#91674
0#
#95841
b1100 '
1#
#100008
0#
#104175
b1101 '
1#
#108342
0#
#112509
b1110 '
1#
#116676
0#
#120843
b1111 '
1#
#125010
0#
#129177
b10000 '
1#
#133344
0#
#137511
b10001 '
1#
#141678
0#
#145845
b10010 '
1#
#150012
0#
#154179
b10011 '
1#
#158346
0#
#162513
b10100 '
1#
#166680
0#
#170847
b10101 '
1#
#175014
0#
#179181
b10110 '
1#
#183348
0#
#187515
b10111 '
1#
#191682
0#
#195849
b11000 '
1#
#200016
0#
#204183
b11001 '
1#
#208350
0#
#212517
b11010 '
1#
#216684
0#
#220851
b11011 '
1#
#225018
0#
#229185
b11100 '
1#
#233352
0#
#237519
b11101 '
1#
#241686
0#
#245853
b11110 '
1#
#250020
0#
#254187
b11111 '
1#
#258354
0#
#262521
b100000 '
1#
#266688
0#
#270855
b100001 '
1#
#275022
0#
#279189
b100010 '
1#
#283356
0#
#287523
b100011 '
1#
#291690
0#
#295857
b100100 '
1#
#300024
0#
#304191
b100101 '
1#
#308358
0#
#312525
b100110 '
1#
#316692
0#
#320859
b100111 '
1#
#325026
0#
#329193
b101000 '
1#
#333360
0#
#337527
b101001 '
1#
#341694
0#
#345861
b101010 '
1#
#350028
0#
#354195
b101011 '
1#
#358362
0#
#362529
b101100 '
1#
#366696
0#
#370863
b101101 '
1#
#375030
0#
#379197
b101110 '
1#
#383364
0#
#387531
b101111 '
1#
#391698
0#
#395865
b110000 '
1#
#400032
0#
#404199
b110001 '
1#
#408366
0#
#412533
b110010 '
1#
#416700
0#
#420867
b110011 '
1#
#425034
0#
#429201
b110100 '
1#
#433368
0#
#437535
b110101 '
1#
#441702
0#
#445869
b110110 '
1#
#450036
0#
#454203
b110111 '
1#
#458370
0#
#462537
b111000 '
1#
#466704
0#
#470871
b111001 '
1#
#475038
0#
#479205
b111010 '
1#
#483372
0#
#487539
b111011 '
1#
#491706
0#
#495873
b111100 '
1#
#500040
0#
#504207
b111101 '
1#
#508374
0#
#512541
b111110 '
1#
#516708
0#
#520875
b111111 '
1#
#525042
0#
#529209
b1000000 '
1#
#533376
0#
#537543
b1000001 '
1#
#541710
0#
#545877
b1000010 '
1#
#550044
0#
#554211
b1000011 '
1#
#558378
0#
#562545
b1000100 '
1#
#566712
0#
#570879
b1000101 '
1#
#575046
0#
#579213
b1000110 '
1#
#583380
0#
#587547
b1000111 '
1#
#591714
0#
#595881
b1001000 '
1#
#600048
0#
#604215
b1001001 '
1#
#608382
0#
#612549
b1001010 '
1#
#616716
0#
#620883
b1001011 '
1#
#625050
0#
#629217
b1001100 '
1#
#633384
0#
#637551
b1001101 '
1#
#641718
0#
#645885
b1001110 '
1#
#650052
0#
#654219
b1001111 '
1#
#658386
0#
#662553
b1010000 '
1#
#666720
0#
#670887
b1010001 '
1#
#675054
0#
#679221
b1010010 '
1#
#683388
0#
#687555
b1010011 '
1#
#691722
0#
#695889
b1010100 '
1#
#700056
0#
#704223
b1010101 '
1#
#708390
0#
#712557
b1010110 '
1#
#716724
0#
#720891
b1010111 '
1#
#725058
0#
#729225
b1011000 '
1#
#733392
0#
#737559
b1011001 '
1#
#741726
0#
#745893
b1011010 '
1#
#750060
0#
#754227
b1011011 '
1#
#758394
0#
#762561
b1011100 '
1#
#766728
0#
#770895
b1011101 '
1#
#775062
0#
#779229
b1011110 '
1#
#783396
0#
#787563
b1011111 '
1#
#791730
0#
#795897
b1100000 '
1#
#800064
0#
#804231
b1100001 '
1#
#808398
0#
#812565
b1100010 '
1#
#816732
0#
#820899
b1100011 '
1#
#825066
0#
#829233
b1100100 '
1#
#833400
0#
#837567
b1100101 '
1#
#841734
0#
#845901
b1100110 '
1#
#850068
0#
#854235
b1100111 '
1#
#858402
0#
#862569
b1101000 '
1#
#866736
0#
#870903
b1101001 '
1#
#875070
0#
#879237
b1101010 '
1#
#883404
0#
#887571
b1101011 '
1#
#891738
0#
#895905
b1101100 '
1#
#900072
0#
#904239
b1101101 '
1#
#908406
0#
#912573
b1101110 '
1#
#916740
0#
#920907
b1101111 '
1#
#925074
0#
#929241
b1110000 '
1#
#933408
0#
#937575
b1110001 '
1#
#941742
0#
#945909
b1110010 '
1#
#950076
0#
#954243
b1110011 '
1#
#958410
0#
#962577
b1110100 '
1#
#966744
0#
#970911
b1110101 '
1#
#975078
0#
#979245
b1110110 '
1#
#983412
0#
#987579
b1110111 '
1#
#991746
0#
#995913
b1111000 '
1#
